terminal_quest/__init__.py
terminal_quest/pizzazz.py
terminal_quest/terminal_quest.py
terminal_quest/mds/.level0_hint.md
terminal_quest/mds/.level1_hint.md
terminal_quest/mds/.level2_hint.md
terminal_quest/mds/.level3_hint.md
terminal_quest/mds/.level4_hint.md
terminal_quest/mds/.level5_hint.md
terminal_quest/mds/.level6_hint.md
terminal_quest/mds/.level7_hint.md
terminal_quest/mds/.level8_hint.md
terminal_quest/mds/.level9_hint.md
terminal_quest/mds/level0.md
terminal_quest/mds/level1.md
terminal_quest/mds/level2.md
terminal_quest/mds/level3.md
terminal_quest/mds/level4.md
terminal_quest/mds/level5.md
terminal_quest/mds/level6.md
terminal_quest/mds/level7.md
terminal_quest/mds/level8.md
terminal_quest/mds/level9.md
terminal_quest-1.2.3.dist-info/DESCRIPTION.rst
terminal_quest-1.2.3.dist-info/METADATA
terminal_quest-1.2.3.dist-info/RECORD
terminal_quest-1.2.3.dist-info/WHEEL
terminal_quest-1.2.3.dist-info/entry_points.txt
terminal_quest-1.2.3.dist-info/metadata.json
terminal_quest-1.2.3.dist-info/top_level.txt
